validateuz/__init__.py
validateuz/main.py
validateuz-0.1.0.dist-info/METADATA
validateuz-0.1.0.dist-info/WHEEL
validateuz-0.1.0.dist-info/top_level.txt
validateuz-0.1.0.dist-info/RECORD
